WebglJiaochengZhongwenban/README.md
WebglJiaochengZhongwenban/__init__.py
WebglJiaochengZhongwenban/__main__.py
WebglJiaochengZhongwenban/file.epub
WebglJiaochengZhongwenban/index.html
WebglJiaochengZhongwenban/css/__init__.py
WebglJiaochengZhongwenban/css/annotations.css
WebglJiaochengZhongwenban/css/main.css
WebglJiaochengZhongwenban/css/normalize.css
WebglJiaochengZhongwenban/css/popup.css
WebglJiaochengZhongwenban/font/__init__.py
WebglJiaochengZhongwenban/font/fontello.eot
WebglJiaochengZhongwenban/font/fontello.svg
WebglJiaochengZhongwenban/font/fontello.ttf
WebglJiaochengZhongwenban/font/fontello.woff
WebglJiaochengZhongwenban/img/__init__.py
WebglJiaochengZhongwenban/img/annotator-glyph-sprite.png
WebglJiaochengZhongwenban/img/annotator-icon-sprite.png
WebglJiaochengZhongwenban/img/apple-touch-icon.png
WebglJiaochengZhongwenban/img/cancelfullscreen.png
WebglJiaochengZhongwenban/img/close.png
WebglJiaochengZhongwenban/img/fullscreen.png
WebglJiaochengZhongwenban/img/loader.gif
WebglJiaochengZhongwenban/img/menu-icon.png
WebglJiaochengZhongwenban/img/save.png
WebglJiaochengZhongwenban/img/saved.png
WebglJiaochengZhongwenban/img/settings-s.png
WebglJiaochengZhongwenban/img/settings.png
WebglJiaochengZhongwenban/img/star.png
WebglJiaochengZhongwenban/js/__init__.py
WebglJiaochengZhongwenban/js/epub.js
WebglJiaochengZhongwenban/js/epub.min.js
WebglJiaochengZhongwenban/js/epub.min.map
WebglJiaochengZhongwenban/js/hooks.min.js
WebglJiaochengZhongwenban/js/hooks.min.map
WebglJiaochengZhongwenban/js/reader.js
WebglJiaochengZhongwenban/js/reader.js.map
WebglJiaochengZhongwenban/js/reader.min.js
WebglJiaochengZhongwenban/js/reader.min.map
WebglJiaochengZhongwenban/js/hooks/__init__.py
WebglJiaochengZhongwenban/js/hooks/extensions/__init__.py
WebglJiaochengZhongwenban/js/hooks/extensions/highlight.js
WebglJiaochengZhongwenban/js/libs/__init__.py
WebglJiaochengZhongwenban/js/libs/jquery.min.js
WebglJiaochengZhongwenban/js/libs/localforage.min.js
webgl_jiaocheng_zhongwenban-2024.3.2.0.dist-info/METADATA
webgl_jiaocheng_zhongwenban-2024.3.2.0.dist-info/WHEEL
webgl_jiaocheng_zhongwenban-2024.3.2.0.dist-info/entry_points.txt
webgl_jiaocheng_zhongwenban-2024.3.2.0.dist-info/top_level.txt
webgl_jiaocheng_zhongwenban-2024.3.2.0.dist-info/RECORD
